{
  "unversionedId": "tutorials/faqs/faq-migration",
  "id": "tutorials/faqs/faq-migration",
  "title": "FAQ：数据迁移",
  "description": "本文列举了在 Zilliz Cloud 进行数据迁移时可能遇到的常见问题及对应解决方法。",
  "source": "@site/docs/tutorials/faqs/faq-migration.md",
  "sourceDirName": "tutorials/faqs",
  "slug": "/docs/faq-migration",
  "permalink": "/docs/faq-migration",
  "draft": false,
  "tags": [],
  "version": "current",
  "sidebarPosition": 5,
  "frontMatter": {
    "slug": "/docs/faq-migration",
    "beta": null,
    "notebook": null,
    "sidebar_position": 5
  },
  "sidebar": "tutorialSidebar",
  "previous": {
    "title": "FAQ：数据导入",
    "permalink": "/docs/faq-data-import"
  },
  "next": {
    "title": "FAQ：资源规划",
    "permalink": "/docs/faq-resource-planning"
  }
}