{
  "created_time": "1706698174",
  "modified_time": "1709263035",
  "name": "list_roles()",
  "owner_id": "ou_8554528ee6e965bad56710acde1c7847",
  "parent_token": "W9SBfQfXUlZAXDdK6nTcop4rnFd",
  "token": "MApVdDl17oU8OixzbMPcgceKnOh",
  "type": "docx",
  "url": "https://zilliverse.feishu.cn/docx/MApVdDl17oU8OixzbMPcgceKnOh",
  "blocks": {
    "items": [
      {
        "block_id": "MApVdDl17oU8OixzbMPcgceKnOh",
        "block_type": 1,
        "children": [
          "APlIdfTrmoXSLnxj7q5cmU6cnwd",
          "N4TNdJ2YJoaOKFxLN4qcOYAnnDc",
          "G8uYd9siQoauCsxUrzfcuMh1n8d",
          "HmjTdsEExoKaCqxzRLVcgW9QnYb",
          "XTvBdtG41olCUtxQ1hhcfjbXnpe",
          "Wy8UdyFgroA7e3xWgZPc590Vndd",
          "UCHFdF5lVoFG1SxcRXYcqPOXn2e",
          "XuugdsmYMoTQEbxKT4Gc56chnLf",
          "LYiydMiviojxiwxkmJkcvp9Gn1e",
          "Hs2OdJyv3ooVKhxK3IlcHMnvnVe",
          "McgEdG5eOoi58ixWirLcM0xjnEf",
          "NNgId6ApXokVWUxE7nAc7kjPnTd",
          "IGwNdADRCoU5USxVClLce1WKnWd",
          "BJaMdujeeoR1MDxZ4BecxrmQnDc",
          "UwKqdko6Uo26FrxT2XCccVlin6c",
          "C72LdMYEiotKpXxANRNcCijDnkf",
          "RjIndPVKzoTUO1xqacScXSWSnud",
          "LT7SdZbLDoWzlAxc5YPcwCtTnwg",
          "OIvHdKJPno7dRhxgDaQcyfhnnEf",
          "D8NGdIHNzoGE7Jx3LeVcMtr1nFh",
          "RZ3vdlgdyotek8xHhpkcNMDXnQ9",
          "B67hdfxC1ovxZFxb2BzcWTOjnqc",
          "DNRTdEL15otjMSxafPlcb2VNn1d",
          "OPy3dHTWEo2vx6x0HxecR442nCd",
          "XG5CdMKhyoXD6Ix2KGLc918Wn3b",
          "VJ7TdQo4vo05mfxYcrRcCer1nuf",
          "B1gSdGNV8oKyF2xmpwxcwUUhnYg",
          "DATkdPyCModJURxcY15cgRkcnXb",
          "N0YtdoONXoDZw0xDNqucgoOfnEA",
          "PzgCdWEkWoiZrIx1WvwcUCqOnZd",
          "QP9NdKuR1o1JXOxkpqWcMYhFnv3",
          "MNKjd1zrooHNPjxMsoKcb0Z2nbc",
          "TBFWdEzFtoRQZYxkHRbcK6vEn3c",
          "TjEddAtldosluxxozYNcuQ0wnff"
        ],
        "page": {
          "elements": [
            {
              "text_run": {
                "content": "list_roles()",
                "text_element_style": {
                  "bold": false,
                  "inline_code": false,
                  "italic": false,
                  "strikethrough": false,
                  "underline": false
                }
              }
            }
          ],
          "style": {
            "align": 1
          }
        },
        "parent_id": ""
      },
      {
        "block_id": "APlIdfTrmoXSLnxj7q5cmU6cnwd",
        "block_type": 2,
        "parent_id": "MApVdDl17oU8OixzbMPcgceKnOh",
        "text": {
          "elements": [
            {
              "text_run": {
                "content": "This operation lists all custom roles.",
                "text_element_style": {
                  "bold": false,
                  "inline_code": false,
                  "italic": false,
                  "strikethrough": false,
                  "underline": false
                }
              }
            }
          ],
          "style": {
            "align": 1,
            "folded": false
          }
        }
      },
      {
        "block_id": "N4TNdJ2YJoaOKFxLN4qcOYAnnDc",
        "block_type": 4,
        "heading2": {
          "elements": [
            {
              "text_run": {
                "content": "Request syntax",
                "text_element_style": {
                  "bold": false,
                  "inline_code": false,
                  "italic": false,
                  "strikethrough": false,
                  "underline": false
                }
              }
            }
          ],
          "style": {
            "align": 1,
            "folded": false
          }
        },
        "parent_id": "MApVdDl17oU8OixzbMPcgceKnOh"
      },
      {
        "block_id": "G8uYd9siQoauCsxUrzfcuMh1n8d",
        "block_type": 14,
        "code": {
          "elements": [
            {
              "text_run": {
                "content": "list_roles(\n    timeout: Optional[float] = None\n",
                "text_element_style": {
                  "bold": false,
                  "inline_code": false,
                  "italic": false,
                  "strikethrough": false,
                  "underline": false
                }
              }
            },
            {
              "text_run": {
                "content": ") -> dict",
                "text_element_style": {
                  "bold": false,
                  "inline_code": false,
                  "italic": false,
                  "strikethrough": false,
                  "underline": false
                }
              }
            }
          ],
          "style": {
            "language": 49,
            "wrap": false
          }
        },
        "parent_id": "MApVdDl17oU8OixzbMPcgceKnOh"
      },
      {
        "block_id": "HmjTdsEExoKaCqxzRLVcgW9QnYb",
        "block_type": 2,
        "parent_id": "MApVdDl17oU8OixzbMPcgceKnOh",
        "text": {
          "elements": [
            {
              "text_run": {
                "content": "PARAMETERS:",
                "text_element_style": {
                  "bold": true,
                  "inline_code": false,
                  "italic": false,
                  "strikethrough": false,
                  "underline": false
                }
              }
            }
          ],
          "style": {
            "align": 1,
            "folded": false
          }
        }
      },
      {
        "block_id": "XTvBdtG41olCUtxQ1hhcfjbXnpe",
        "block_type": 12,
        "bullet": {
          "elements": [
            {
              "text_run": {
                "content": "timeout",
                "text_element_style": {
                  "bold": true,
                  "inline_code": false,
                  "italic": false,
                  "strikethrough": false,
                  "underline": false
                }
              }
            },
            {
              "text_run": {
                "content": " (",
                "text_element_style": {
                  "bold": false,
                  "inline_code": false,
                  "italic": false,
                  "strikethrough": false,
                  "underline": false
                }
              }
            },
            {
              "text_run": {
                "content": "float ",
                "text_element_style": {
                  "bold": false,
                  "inline_code": false,
                  "italic": true,
                  "strikethrough": false,
                  "underline": false
                }
              }
            },
            {
              "text_run": {
                "content": "|",
                "text_element_style": {
                  "bold": false,
                  "inline_code": false,
                  "italic": false,
                  "strikethrough": false,
                  "underline": false
                }
              }
            },
            {
              "text_run": {
                "content": " None",
                "text_element_style": {
                  "bold": false,
                  "inline_code": false,
                  "italic": true,
                  "strikethrough": false,
                  "underline": false
                }
              }
            },
            {
              "text_run": {
                "content": ")  ",
                "text_element_style": {
                  "bold": false,
                  "inline_code": false,
                  "italic": false,
                  "strikethrough": false,
                  "underline": false
                }
              }
            }
          ],
          "style": {
            "align": 1,
            "folded": false
          }
        },
        "children": [
          "PanldHO6ooawhMxbJk6cu9LFnee",
          "PZqHdEIDVoLFTZxHCL9cm69gnqP"
        ],
        "parent_id": "MApVdDl17oU8OixzbMPcgceKnOh"
      },
      {
        "block_id": "PanldHO6ooawhMxbJk6cu9LFnee",
        "block_type": 2,
        "parent_id": "XTvBdtG41olCUtxQ1hhcfjbXnpe",
        "text": {
          "elements": [
            {
              "text_run": {
                "content": "The timeout duration for this operation. ",
                "text_element_style": {
                  "bold": false,
                  "inline_code": false,
                  "italic": false,
                  "strikethrough": false,
                  "underline": false
                }
              }
            }
          ],
          "style": {
            "align": 1,
            "folded": false
          }
        }
      },
      {
        "block_id": "PZqHdEIDVoLFTZxHCL9cm69gnqP",
        "block_type": 2,
        "parent_id": "XTvBdtG41olCUtxQ1hhcfjbXnpe",
        "text": {
          "elements": [
            {
              "text_run": {
                "content": "Setting this to ",
                "text_element_style": {
                  "bold": false,
                  "inline_code": false,
                  "italic": false,
                  "strikethrough": false,
                  "underline": false
                }
              }
            },
            {
              "text_run": {
                "content": "None",
                "text_element_style": {
                  "bold": true,
                  "inline_code": false,
                  "italic": false,
                  "strikethrough": false,
                  "underline": false
                }
              }
            },
            {
              "text_run": {
                "content": " indicates that this operation timeouts when any response arrives or any error occurs.",
                "text_element_style": {
                  "bold": false,
                  "inline_code": false,
                  "italic": false,
                  "strikethrough": false,
                  "underline": false
                }
              }
            }
          ],
          "style": {
            "align": 1,
            "folded": false
          }
        }
      },
      {
        "block_id": "Wy8UdyFgroA7e3xWgZPc590Vndd",
        "block_type": 2,
        "parent_id": "MApVdDl17oU8OixzbMPcgceKnOh",
        "text": {
          "elements": [
            {
              "text_run": {
                "content": "RETURN TYPE:",
                "text_element_style": {
                  "bold": true,
                  "inline_code": false,
                  "italic": false,
                  "strikethrough": false,
                  "underline": false
                }
              }
            }
          ],
          "style": {
            "align": 1,
            "folded": false
          }
        }
      },
      {
        "block_id": "UCHFdF5lVoFG1SxcRXYcqPOXn2e",
        "block_type": 2,
        "parent_id": "MApVdDl17oU8OixzbMPcgceKnOh",
        "text": {
          "elements": [
            {
              "text_run": {
                "content": "list",
                "text_element_style": {
                  "bold": false,
                  "inline_code": false,
                  "italic": true,
                  "strikethrough": false,
                  "underline": false
                }
              }
            }
          ],
          "style": {
            "align": 1,
            "folded": false
          }
        }
      },
      {
        "block_id": "XuugdsmYMoTQEbxKT4Gc56chnLf",
        "block_type": 2,
        "parent_id": "MApVdDl17oU8OixzbMPcgceKnOh",
        "text": {
          "elements": [
            {
              "text_run": {
                "content": "RETURNS:",
                "text_element_style": {
                  "bold": true,
                  "inline_code": false,
                  "italic": false,
                  "strikethrough": false,
                  "underline": false
                }
              }
            }
          ],
          "style": {
            "align": 1,
            "folded": false
          }
        }
      },
      {
        "block_id": "LYiydMiviojxiwxkmJkcvp9Gn1e",
        "block_type": 2,
        "parent_id": "MApVdDl17oU8OixzbMPcgceKnOh",
        "text": {
          "elements": [
            {
              "text_run": {
                "content": "A list of role names.",
                "text_element_style": {
                  "bold": false,
                  "inline_code": false,
                  "italic": false,
                  "strikethrough": false,
                  "underline": false
                }
              }
            }
          ],
          "style": {
            "align": 1,
            "folded": false
          }
        }
      },
      {
        "block_id": "Hs2OdJyv3ooVKhxK3IlcHMnvnVe",
        "block_type": 2,
        "parent_id": "MApVdDl17oU8OixzbMPcgceKnOh",
        "text": {
          "elements": [
            {
              "text_run": {
                "content": "EXCEPTIONS:",
                "text_element_style": {
                  "bold": true,
                  "inline_code": false,
                  "italic": false,
                  "strikethrough": false,
                  "underline": false
                }
              }
            }
          ],
          "style": {
            "align": 1,
            "folded": false
          }
        }
      },
      {
        "block_id": "McgEdG5eOoi58ixWirLcM0xjnEf",
        "block_type": 12,
        "bullet": {
          "elements": [
            {
              "text_run": {
                "content": "MilvusException",
                "text_element_style": {
                  "bold": true,
                  "inline_code": false,
                  "italic": false,
                  "strikethrough": false,
                  "underline": false
                }
              }
            }
          ],
          "style": {
            "align": 1,
            "folded": false
          }
        },
        "children": [
          "YGOwdZYaIoRx7nx1Sy4cNpJhnNh"
        ],
        "parent_id": "MApVdDl17oU8OixzbMPcgceKnOh"
      },
      {
        "block_id": "YGOwdZYaIoRx7nx1Sy4cNpJhnNh",
        "block_type": 2,
        "parent_id": "McgEdG5eOoi58ixWirLcM0xjnEf",
        "text": {
          "elements": [
            {
              "text_run": {
                "content": "This exception will be raised when any error occurs during this operation.",
                "text_element_style": {
                  "bold": false,
                  "inline_code": false,
                  "italic": false,
                  "strikethrough": false,
                  "underline": false
                }
              }
            }
          ],
          "style": {
            "align": 1,
            "folded": false
          }
        }
      },
      {
        "block_id": "NNgId6ApXokVWUxE7nAc7kjPnTd",
        "block_type": 12,
        "bullet": {
          "elements": [
            {
              "text_run": {
                "content": "BaseException",
                "text_element_style": {
                  "bold": true,
                  "inline_code": false,
                  "italic": false,
                  "strikethrough": false,
                  "underline": false
                }
              }
            }
          ],
          "style": {
            "align": 1,
            "folded": false
          }
        },
        "children": [
          "QqaVdQbxnoiHrxxLbzucwIP6nod"
        ],
        "parent_id": "MApVdDl17oU8OixzbMPcgceKnOh"
      },
      {
        "block_id": "QqaVdQbxnoiHrxxLbzucwIP6nod",
        "block_type": 2,
        "parent_id": "NNgId6ApXokVWUxE7nAc7kjPnTd",
        "text": {
          "elements": [
            {
              "text_run": {
                "content": "This exception will be raised when this operation fails.",
                "text_element_style": {
                  "bold": false,
                  "inline_code": false,
                  "italic": false,
                  "strikethrough": false,
                  "underline": false
                }
              }
            }
          ],
          "style": {
            "align": 1,
            "folded": false
          }
        }
      },
      {
        "block_id": "IGwNdADRCoU5USxVClLce1WKnWd",
        "block_type": 4,
        "heading2": {
          "elements": [
            {
              "text_run": {
                "content": "Example",
                "text_element_style": {
                  "bold": false,
                  "inline_code": false,
                  "italic": false,
                  "strikethrough": false,
                  "underline": false
                }
              }
            }
          ],
          "style": {
            "align": 1,
            "folded": false
          }
        },
        "parent_id": "MApVdDl17oU8OixzbMPcgceKnOh"
      },
      {
        "block_id": "BJaMdujeeoR1MDxZ4BecxrmQnDc",
        "block_type": 2,
        "parent_id": "MApVdDl17oU8OixzbMPcgceKnOh",
        "text": {
          "elements": [
            {
              "text_run": {
                "content": "<include target=\"milvus\">",
                "text_element_style": {
                  "bold": false,
                  "inline_code": false,
                  "italic": false,
                  "strikethrough": false,
                  "underline": false
                }
              }
            }
          ],
          "style": {
            "align": 1,
            "folded": false
          }
        }
      },
      {
        "block_id": "UwKqdko6Uo26FrxT2XCccVlin6c",
        "block_type": 14,
        "code": {
          "elements": [
            {
              "text_run": {
                "content": "from pymilvus import MilvusClient\n\n# 1. Create a milvus client\nclient = MilvusClient(\n    uri=\"http://localhost:19530\",\n    token=\"root:Milvus\"\n)\n\n# 2. Create a role\nclient.create_role(role_name=\"read_only\")\n\n# 3. List all roles\nclient.list_roles()\n\n",
                "text_element_style": {
                  "bold": false,
                  "inline_code": false,
                  "italic": false,
                  "strikethrough": false,
                  "underline": false
                }
              }
            },
            {
              "text_run": {
                "content": "# ['admin', 'public', 'read_only']",
                "text_element_style": {
                  "bold": false,
                  "inline_code": false,
                  "italic": false,
                  "strikethrough": false,
                  "underline": false
                }
              }
            }
          ],
          "style": {
            "language": 49,
            "wrap": false
          }
        },
        "parent_id": "MApVdDl17oU8OixzbMPcgceKnOh"
      },
      {
        "block_id": "C72LdMYEiotKpXxANRNcCijDnkf",
        "block_type": 2,
        "parent_id": "MApVdDl17oU8OixzbMPcgceKnOh",
        "text": {
          "elements": [
            {
              "text_run": {
                "content": "</include>",
                "text_element_style": {
                  "bold": false,
                  "inline_code": false,
                  "italic": false,
                  "strikethrough": false,
                  "underline": false
                }
              }
            }
          ],
          "style": {
            "align": 1,
            "folded": false
          }
        }
      },
      {
        "block_id": "RjIndPVKzoTUO1xqacScXSWSnud",
        "block_type": 2,
        "parent_id": "MApVdDl17oU8OixzbMPcgceKnOh",
        "text": {
          "elements": [
            {
              "text_run": {
                "content": "<include target=\"zilliz\">",
                "text_element_style": {
                  "bold": false,
                  "inline_code": false,
                  "italic": false,
                  "strikethrough": false,
                  "underline": false
                }
              }
            }
          ],
          "style": {
            "align": 1,
            "folded": false
          }
        }
      },
      {
        "block_id": "LT7SdZbLDoWzlAxc5YPcwCtTnwg",
        "block_type": 14,
        "code": {
          "elements": [
            {
              "text_run": {
                "content": "from pymilvus import MilvusClient\n\n# 1. Create a milvus client\nclient = MilvusClient(\n    uri=\"https://inxx-xxxxxxxxxxxx.api.gcp-us-west1.zillizcloud.com:19530\",\n    token=\"user:password\"\n)\n\n# 2. List all roles\nclient.list_roles()\n\n",
                "text_element_style": {
                  "bold": false,
                  "inline_code": false,
                  "italic": false,
                  "strikethrough": false,
                  "underline": false
                }
              }
            },
            {
              "text_run": {
                "content": "# ['db_admin', 'db_ro', 'db_rw']",
                "text_element_style": {
                  "bold": false,
                  "inline_code": false,
                  "italic": false,
                  "strikethrough": false,
                  "underline": false
                }
              }
            }
          ],
          "style": {
            "language": 49,
            "wrap": false
          }
        },
        "parent_id": "MApVdDl17oU8OixzbMPcgceKnOh"
      },
      {
        "block_id": "OIvHdKJPno7dRhxgDaQcyfhnnEf",
        "block_type": 19,
        "callout": {
          "background_color": 2,
          "border_color": 2,
          "emoji_id": "blue_book"
        },
        "children": [
          "MQX3dP3nEoubI2xZjBmccPXTnrh",
          "AMLWdrutBoWX09xgCA1cKCA0nVd"
        ],
        "parent_id": "MApVdDl17oU8OixzbMPcgceKnOh"
      },
      {
        "block_id": "MQX3dP3nEoubI2xZjBmccPXTnrh",
        "block_type": 2,
        "parent_id": "OIvHdKJPno7dRhxgDaQcyfhnnEf",
        "text": {
          "elements": [
            {
              "text_run": {
                "content": "Notes",
                "text_element_style": {
                  "bold": false,
                  "inline_code": false,
                  "italic": false,
                  "strikethrough": false,
                  "underline": false
                }
              }
            }
          ],
          "style": {
            "align": 1,
            "folded": false
          }
        }
      },
      {
        "block_id": "AMLWdrutBoWX09xgCA1cKCA0nVd",
        "block_type": 2,
        "parent_id": "OIvHdKJPno7dRhxgDaQcyfhnnEf",
        "text": {
          "elements": [
            {
              "text_run": {
                "content": "Each Zilliz Cloud cluster has three built-in roles, namely, ",
                "text_element_style": {
                  "bold": false,
                  "inline_code": false,
                  "italic": false,
                  "strikethrough": false,
                  "underline": false
                }
              }
            },
            {
              "text_run": {
                "content": "db\\_ro",
                "text_element_style": {
                  "bold": true,
                  "inline_code": false,
                  "italic": false,
                  "strikethrough": false,
                  "underline": false
                }
              }
            },
            {
              "text_run": {
                "content": ", ",
                "text_element_style": {
                  "bold": false,
                  "inline_code": false,
                  "italic": false,
                  "strikethrough": false,
                  "underline": false
                }
              }
            },
            {
              "text_run": {
                "content": "db\\_rw",
                "text_element_style": {
                  "bold": true,
                  "inline_code": false,
                  "italic": false,
                  "strikethrough": false,
                  "underline": false
                }
              }
            },
            {
              "text_run": {
                "content": ", and ",
                "text_element_style": {
                  "bold": false,
                  "inline_code": false,
                  "italic": false,
                  "strikethrough": false,
                  "underline": false
                }
              }
            },
            {
              "text_run": {
                "content": "db\\_admin",
                "text_element_style": {
                  "bold": true,
                  "inline_code": false,
                  "italic": false,
                  "strikethrough": false,
                  "underline": false
                }
              }
            },
            {
              "text_run": {
                "content": ". For details, refer to ",
                "text_element_style": {
                  "bold": false,
                  "inline_code": false,
                  "italic": false,
                  "strikethrough": false,
                  "underline": false
                }
              }
            },
            {
              "text_run": {
                "content": "Cluster Built-in Roles",
                "text_element_style": {
                  "bold": false,
                  "inline_code": false,
                  "italic": false,
                  "link": {
                    "url": "https%3A%2F%2Fdocs.zilliz.com%2Fdocs%2Fuser-roles%23cluster-built-in-roles"
                  },
                  "strikethrough": false,
                  "underline": false
                }
              }
            },
            {
              "text_run": {
                "content": ".",
                "text_element_style": {
                  "bold": false,
                  "inline_code": false,
                  "italic": false,
                  "strikethrough": false,
                  "underline": false
                }
              }
            }
          ],
          "style": {
            "align": 1,
            "folded": false
          }
        }
      },
      {
        "block_id": "D8NGdIHNzoGE7Jx3LeVcMtr1nFh",
        "block_type": 2,
        "parent_id": "MApVdDl17oU8OixzbMPcgceKnOh",
        "text": {
          "elements": [
            {
              "text_run": {
                "content": "</include>",
                "text_element_style": {
                  "bold": false,
                  "inline_code": false,
                  "italic": false,
                  "strikethrough": false,
                  "underline": false
                }
              }
            }
          ],
          "style": {
            "align": 1,
            "folded": false
          }
        }
      },
      {
        "block_id": "RZ3vdlgdyotek8xHhpkcNMDXnQ9",
        "block_type": 4,
        "heading2": {
          "elements": [
            {
              "text_run": {
                "content": "Related methods",
                "text_element_style": {
                  "bold": false,
                  "inline_code": false,
                  "italic": false,
                  "strikethrough": false,
                  "underline": false
                }
              }
            }
          ],
          "style": {
            "align": 1,
            "folded": false
          }
        },
        "parent_id": "MApVdDl17oU8OixzbMPcgceKnOh"
      },
      {
        "block_id": "B67hdfxC1ovxZFxb2BzcWTOjnqc",
        "block_type": 2,
        "parent_id": "MApVdDl17oU8OixzbMPcgceKnOh",
        "text": {
          "elements": [
            {
              "text_run": {
                "content": "<include target=\"milvus\">",
                "text_element_style": {
                  "bold": false,
                  "inline_code": false,
                  "italic": false,
                  "strikethrough": false,
                  "underline": false
                }
              }
            }
          ],
          "style": {
            "align": 1,
            "folded": false
          }
        }
      },
      {
        "block_id": "DNRTdEL15otjMSxafPlcb2VNn1d",
        "block_type": 12,
        "bullet": {
          "elements": [
            {
              "mention_doc": {
                "obj_type": 22,
                "text_element_style": {
                  "bold": false,
                  "inline_code": false,
                  "italic": false,
                  "strikethrough": false,
                  "underline": false
                },
                "title": "create_role()",
                "token": "OUz3drncZo1Er8xyITZcYz66nWE",
                "url": "https://zilliverse.feishu.cn/docx/OUz3drncZo1Er8xyITZcYz66nWE"
              }
            }
          ],
          "style": {
            "align": 1,
            "folded": false
          }
        },
        "parent_id": "MApVdDl17oU8OixzbMPcgceKnOh"
      },
      {
        "block_id": "OPy3dHTWEo2vx6x0HxecR442nCd",
        "block_type": 2,
        "parent_id": "MApVdDl17oU8OixzbMPcgceKnOh",
        "text": {
          "elements": [
            {
              "text_run": {
                "content": "</include>",
                "text_element_style": {
                  "bold": false,
                  "inline_code": false,
                  "italic": false,
                  "strikethrough": false,
                  "underline": false
                }
              }
            }
          ],
          "style": {
            "align": 1,
            "folded": false
          }
        }
      },
      {
        "block_id": "XG5CdMKhyoXD6Ix2KGLc918Wn3b",
        "block_type": 12,
        "bullet": {
          "elements": [
            {
              "mention_doc": {
                "obj_type": 22,
                "text_element_style": {
                  "bold": false,
                  "inline_code": false,
                  "italic": false,
                  "strikethrough": false,
                  "underline": false
                },
                "title": "describe_role()",
                "token": "JJz3dFrE2oJP3AxySWYcJlf4nMh",
                "url": "https://zilliverse.feishu.cn/docx/JJz3dFrE2oJP3AxySWYcJlf4nMh"
              }
            }
          ],
          "style": {
            "align": 1,
            "folded": false
          }
        },
        "parent_id": "MApVdDl17oU8OixzbMPcgceKnOh"
      },
      {
        "block_id": "VJ7TdQo4vo05mfxYcrRcCer1nuf",
        "block_type": 2,
        "parent_id": "MApVdDl17oU8OixzbMPcgceKnOh",
        "text": {
          "elements": [
            {
              "text_run": {
                "content": "<include target=\"milvus\">",
                "text_element_style": {
                  "bold": false,
                  "inline_code": false,
                  "italic": false,
                  "strikethrough": false,
                  "underline": false
                }
              }
            }
          ],
          "style": {
            "align": 1,
            "folded": false
          }
        }
      },
      {
        "block_id": "B1gSdGNV8oKyF2xmpwxcwUUhnYg",
        "block_type": 12,
        "bullet": {
          "elements": [
            {
              "mention_doc": {
                "obj_type": 22,
                "text_element_style": {
                  "bold": false,
                  "inline_code": false,
                  "italic": false,
                  "strikethrough": false,
                  "underline": false
                },
                "title": "drop_role()",
                "token": "Vmxpd3MttodOE3x3V11cVTeunDh",
                "url": "https://zilliverse.feishu.cn/docx/Vmxpd3MttodOE3x3V11cVTeunDh"
              }
            }
          ],
          "style": {
            "align": 1,
            "folded": false
          }
        },
        "parent_id": "MApVdDl17oU8OixzbMPcgceKnOh"
      },
      {
        "block_id": "DATkdPyCModJURxcY15cgRkcnXb",
        "block_type": 12,
        "bullet": {
          "elements": [
            {
              "mention_doc": {
                "obj_type": 22,
                "text_element_style": {
                  "bold": false,
                  "inline_code": false,
                  "italic": false,
                  "strikethrough": false,
                  "underline": false
                },
                "title": "grant_privilege()",
                "token": "W39Wdr7S6ohrtfxI8r7cyTeInlb",
                "url": "https://zilliverse.feishu.cn/docx/W39Wdr7S6ohrtfxI8r7cyTeInlb"
              }
            }
          ],
          "style": {
            "align": 1,
            "folded": false
          }
        },
        "parent_id": "MApVdDl17oU8OixzbMPcgceKnOh"
      },
      {
        "block_id": "N0YtdoONXoDZw0xDNqucgoOfnEA",
        "block_type": 2,
        "parent_id": "MApVdDl17oU8OixzbMPcgceKnOh",
        "text": {
          "elements": [
            {
              "text_run": {
                "content": "</include>",
                "text_element_style": {
                  "bold": false,
                  "inline_code": false,
                  "italic": false,
                  "strikethrough": false,
                  "underline": false
                }
              }
            }
          ],
          "style": {
            "align": 1,
            "folded": false
          }
        }
      },
      {
        "block_id": "PzgCdWEkWoiZrIx1WvwcUCqOnZd",
        "block_type": 12,
        "bullet": {
          "elements": [
            {
              "mention_doc": {
                "obj_type": 22,
                "text_element_style": {
                  "bold": false,
                  "inline_code": false,
                  "italic": false,
                  "strikethrough": false,
                  "underline": false
                },
                "title": "grant_role()",
                "token": "DsnpdZuDGo77TYxFuYvcDpOgnIf",
                "url": "https://zilliverse.feishu.cn/docx/DsnpdZuDGo77TYxFuYvcDpOgnIf"
              }
            }
          ],
          "style": {
            "align": 1,
            "folded": false
          }
        },
        "parent_id": "MApVdDl17oU8OixzbMPcgceKnOh"
      },
      {
        "block_id": "QP9NdKuR1o1JXOxkpqWcMYhFnv3",
        "block_type": 2,
        "parent_id": "MApVdDl17oU8OixzbMPcgceKnOh",
        "text": {
          "elements": [
            {
              "text_run": {
                "content": "<include target=\"milvus\">",
                "text_element_style": {
                  "bold": false,
                  "inline_code": false,
                  "italic": false,
                  "strikethrough": false,
                  "underline": false
                }
              }
            }
          ],
          "style": {
            "align": 1,
            "folded": false
          }
        }
      },
      {
        "block_id": "MNKjd1zrooHNPjxMsoKcb0Z2nbc",
        "block_type": 12,
        "bullet": {
          "elements": [
            {
              "mention_doc": {
                "obj_type": 22,
                "text_element_style": {
                  "bold": false,
                  "inline_code": false,
                  "italic": false,
                  "strikethrough": false,
                  "underline": false
                },
                "title": "revoke_privileges()",
                "token": "UP2GdfHHzoIQ56x2JvScs0sAnzh",
                "url": "https://zilliverse.feishu.cn/docx/UP2GdfHHzoIQ56x2JvScs0sAnzh"
              }
            }
          ],
          "style": {
            "align": 1,
            "folded": false
          }
        },
        "parent_id": "MApVdDl17oU8OixzbMPcgceKnOh"
      },
      {
        "block_id": "TBFWdEzFtoRQZYxkHRbcK6vEn3c",
        "block_type": 2,
        "parent_id": "MApVdDl17oU8OixzbMPcgceKnOh",
        "text": {
          "elements": [
            {
              "text_run": {
                "content": "</include>",
                "text_element_style": {
                  "bold": false,
                  "inline_code": false,
                  "italic": false,
                  "strikethrough": false,
                  "underline": false
                }
              }
            }
          ],
          "style": {
            "align": 1,
            "folded": false
          }
        }
      },
      {
        "block_id": "TjEddAtldosluxxozYNcuQ0wnff",
        "block_type": 12,
        "bullet": {
          "elements": [
            {
              "mention_doc": {
                "obj_type": 22,
                "text_element_style": {
                  "bold": false,
                  "inline_code": false,
                  "italic": false,
                  "strikethrough": false,
                  "underline": false
                },
                "title": "revoke_role()",
                "token": "JJOId59ePoMLefxz1ChcBZ6inOh",
                "url": "https://zilliverse.feishu.cn/docx/JJOId59ePoMLefxz1ChcBZ6inOh"
              }
            }
          ],
          "style": {
            "align": 1,
            "folded": false
          }
        },
        "parent_id": "MApVdDl17oU8OixzbMPcgceKnOh"
      }
    ],
    "counts": 41
  },
  "slug": "Authentication-list_roles"
}